nginx_error_log/__init__.py
nginx_error_log/_helpers.py
nginx_error_log/_parser.py
nginx_error_log/_utils.py
nginx_error_log-0.1.1.dist-info/LICENSE.txt
nginx_error_log-0.1.1.dist-info/WHEEL
nginx_error_log-0.1.1.dist-info/METADATA
nginx_error_log-0.1.1.dist-info/RECORD
