Metadata-Version: 2.1
Name: nginx-error-log
Version: 0.1.1
Summary: Nginx error log parser.
Home-page: https://github.com/madsmtm/nginx-error-log/
License: MIT
Keywords: Nginx Error Log Parser error_log
Author: Mads Marquart
Author-email: madsmtm@gmail.com
Requires-Python: ~=3.6
Classifier: Development Status :: 1 - Planning
Classifier: Intended Audience :: Developers
Classifier: Intended Audience :: Information Technology
Classifier: License :: OSI Approved :: MIT License
Classifier: Operating System :: OS Independent
Classifier: Natural Language :: English
Classifier: Programming Language :: Python
Classifier: Programming Language :: Python :: 3
Classifier: Programming Language :: Python :: 3 :: Only
Classifier: Programming Language :: Python :: 3.6
Classifier: Programming Language :: Python :: 3.7
Classifier: Programming Language :: Python :: Implementation :: CPython
Classifier: Topic :: Internet :: Log Analysis
Classifier: Topic :: Internet :: WWW/HTTP
Classifier: Topic :: Software Development :: Libraries
Classifier: Topic :: Software Development :: Libraries :: Python Modules
Classifier: Topic :: System :: Logging
Classifier: Topic :: System :: Networking
Classifier: Topic :: System :: Networking :: Monitoring
Requires-Dist: dataclasses
Requires-Dist: black ; extra == "dev"
Requires-Dist: pytest ; extra == "test"
Requires-Dist: pytest-raises ; extra == "test"
Project-URL: Repository, https://github.com/madsmtm/nginx-error-log/
Provides-Extra: dev
Provides-Extra: test
